antaresia/__init__.py
antaresia/__main__.py
antaresia/checks.py
antaresia/cli.py
antaresia/config_functions.py
antaresia/exceptions.py
antaresia/filters.py
antaresia/loaders.py
antaresia/types.py
antaresia-0.0.1a6.dist-info/entry_points.txt
antaresia-0.0.1a6.dist-info/LICENSE
antaresia-0.0.1a6.dist-info/WHEEL
antaresia-0.0.1a6.dist-info/METADATA
antaresia-0.0.1a6.dist-info/RECORD
