Metadata-Version: 2.1
Name: antaresia
Version: 0.0.1a6
Summary: Antaresia is subset of Python to write configuration files.
Home-page: https://gitlab.com/jmcs/antaresia
License: UNKNOWN
Author: João Santos
Author-email: jmcs@jsantos.eu
Requires-Python: >=3.6
Classifier: Intended Audience :: Developers
Classifier: License :: OSI Approved :: MIT License
Classifier: Development Status :: 3 - Alpha
Classifier: Programming Language :: Python :: 3
Classifier: Topic :: Software Development :: Libraries :: Python Modules
Requires-Dist: mypy
Requires-Dist: pyyaml; extra == "yaml"
Provides-Extra: yaml
